odoo9_addon_purchase_stock_picking_return_invoicing-9.0.1.1.0-py2.7-nspkg.pth
odoo9_addon_purchase_stock_picking_return_invoicing-9.0.1.1.0.dist-info/DESCRIPTION.rst
odoo9_addon_purchase_stock_picking_return_invoicing-9.0.1.1.0.dist-info/METADATA
odoo9_addon_purchase_stock_picking_return_invoicing-9.0.1.1.0.dist-info/RECORD
odoo9_addon_purchase_stock_picking_return_invoicing-9.0.1.1.0.dist-info/WHEEL
odoo9_addon_purchase_stock_picking_return_invoicing-9.0.1.1.0.dist-info/metadata.json
odoo9_addon_purchase_stock_picking_return_invoicing-9.0.1.1.0.dist-info/namespace_packages.txt
odoo9_addon_purchase_stock_picking_return_invoicing-9.0.1.1.0.dist-info/top_level.txt
odoo_addons/purchase_stock_picking_return_invoicing/README.rst
odoo_addons/purchase_stock_picking_return_invoicing/__init__.py
odoo_addons/purchase_stock_picking_return_invoicing/__openerp__.py
odoo_addons/purchase_stock_picking_return_invoicing/i18n/ar.po
odoo_addons/purchase_stock_picking_return_invoicing/i18n/bg.po
odoo_addons/purchase_stock_picking_return_invoicing/i18n/bs.po
odoo_addons/purchase_stock_picking_return_invoicing/i18n/ca.po
odoo_addons/purchase_stock_picking_return_invoicing/i18n/cs.po
odoo_addons/purchase_stock_picking_return_invoicing/i18n/de.po
odoo_addons/purchase_stock_picking_return_invoicing/i18n/el_GR.po
odoo_addons/purchase_stock_picking_return_invoicing/i18n/en_GB.po
odoo_addons/purchase_stock_picking_return_invoicing/i18n/es.po
odoo_addons/purchase_stock_picking_return_invoicing/i18n/es_CR.po
odoo_addons/purchase_stock_picking_return_invoicing/i18n/es_EC.po
odoo_addons/purchase_stock_picking_return_invoicing/i18n/es_MX.po
odoo_addons/purchase_stock_picking_return_invoicing/i18n/et.po
odoo_addons/purchase_stock_picking_return_invoicing/i18n/fi.po
odoo_addons/purchase_stock_picking_return_invoicing/i18n/fr.po
odoo_addons/purchase_stock_picking_return_invoicing/i18n/fr_CA.po
odoo_addons/purchase_stock_picking_return_invoicing/i18n/fr_CH.po
odoo_addons/purchase_stock_picking_return_invoicing/i18n/fr_FR.po
odoo_addons/purchase_stock_picking_return_invoicing/i18n/gl.po
odoo_addons/purchase_stock_picking_return_invoicing/i18n/hr.po
odoo_addons/purchase_stock_picking_return_invoicing/i18n/hr_HR.po
odoo_addons/purchase_stock_picking_return_invoicing/i18n/hu.po
odoo_addons/purchase_stock_picking_return_invoicing/i18n/id.po
odoo_addons/purchase_stock_picking_return_invoicing/i18n/it.po
odoo_addons/purchase_stock_picking_return_invoicing/i18n/ja.po
odoo_addons/purchase_stock_picking_return_invoicing/i18n/lt.po
